setup.py
timesketch_import_client/__init__.py
timesketch_import_client/helper.py
timesketch_import_client/helper_test.py
timesketch_import_client/importer.py
timesketch_import_client/importer_test.py
timesketch_import_client/utils.py
timesketch_import_client/version.py
timesketch_import_client.egg-info/PKG-INFO
timesketch_import_client.egg-info/SOURCES.txt
timesketch_import_client.egg-info/dependency_links.txt
timesketch_import_client.egg-info/entry_points.txt
timesketch_import_client.egg-info/not-zip-safe
timesketch_import_client.egg-info/requires.txt
timesketch_import_client.egg-info/top_level.txt
timesketch_import_client/data/__init__.py
timesketch_import_client/data/formatter.yaml
tools/__init__.py
tools/timesketch_importer.py